[{"id":"3cad85ce-c6dd-4e43-b1c2-ee123c14e6ec","name":"ball-fuchsia","setName":"capture-the-flag","cssClass":"fuchsia r1 pink-b thick","pushable":true,"fragile":false,"reactions":""},{"id":"f280650a-17cd-424e-aca5-f01d8f144fa5","name":"ball-sky-blue","setName":"capture-the-flag","cssClass":"blue r1 sky-blue-b thick","pushable":true,"fragile":false,"reactions":""},{"id":"673ca035-25db-4761-b9bf-42198af5daea","name":"fuchsia-goal","setName":"capture-the-flag","cssClass":"fuchsia-b thick","pushable":false,"fragile":false,"reactions":"fuchsia-goal"},{"id":"805cd6a1-6384-4b90-b72d-b5d7af36d3be","name":"sky-blue-goal","setName":"capture-the-flag","cssClass":"sky-blue-b thick","pushable":false,"fragile":false,"reactions":"sky-blue-goal"},{"id":"d7d98f29-63a8-4cf8-8a90-9db7cb9f86ad","name":"tutorial-goal-fuschsia","setName":"capture-the-flag","cssClass":"fuchsia-b thick","pushable":false,"fragile":false,"reactions":"tutorial-goal"},{"id":"2fb72c65-64b4-40b0-b169-f82b443d4b80","name":"tutorial-goal-sky-blue","setName":"capture-the-flag","cssClass":"sky-blue-b thick","pushable":false,"fragile":false,"reactions":"tutorial-goal"}]